{"0": "Backend Auth Module", "1": "Backend Domain Entities", "2": "Angular Build Config", "3": "Frontend Markings Service", "4": "Frontend Dependencies", "5": "Frontend App Shell & Routing", "6": "Backend Package Config", "7": "Backend Dev Dependencies", "8": "Backend TypeScript Config", "9": "Backend Runtime Dependencies", "10": "Architecture Concepts", "11": "Map Component", "12": "E2E Test Config", "13": "NestJS CLI Config", "14": "Frontend API Proxy", "15": "Backend Build Config", "16": "VS Code Launch", "17": "VS Code Tasks", "18": "VS Code Extensions", "19": "ESLint Config", "20": "Frontend TS App Config", "21": "Frontend TS Base Config", "22": "Frontend TS Spec Config"}